chenetdb/__init__.py
chenetdb/client.py
chenetdb/py.typed
chenetdb-0.0.1.dist-info/WHEEL
chenetdb-0.0.1.dist-info/METADATA
chenetdb-0.0.1.dist-info/RECORD
