Metadata-Version: 2.3
Name: chenetdb
Version: 0.0.1
Summary: Add your description here
Author-email: slouis@email.sc.edu
Requires-Dist: pymongo>=4.16.0
Requires-Python: >=3.10
